MANIFEST.in
README.md
conf.py
setup.py
version.py
processfiles/__init__.py
processfiles/base.py
processfiles/files.py
processfiles/filetools.py
processfiles/objs.py
processfiles/timing.py
processfiles.egg-info/PKG-INFO
processfiles.egg-info/SOURCES.txt
processfiles.egg-info/dependency_links.txt
processfiles.egg-info/top_level.txt