Metadata-Version: 1.2
Name: processfiles
Version: 0.1.3
Summary: Python local file process tracker
Home-page: https://github.com/whoopnip/py-process-files/
Author: Nick DeRobertis
Author-email: whoopnip@gmail.com
License: MIT
Project-URL: Code, https://github.com/whoopnip/py-process-files/
Project-URL: Documentation, https://whoopnip.github.io/py-process-files/
Platform: UNKNOWN
Classifier: Development Status :: 3 - Alpha
Classifier: Intended Audience :: Developers
Classifier: Programming Language :: Python :: 3.6
Classifier: Programming Language :: Python :: 3.7
